LICENSE
README.md
setup.py
noblklog/__init__.py
noblklog/stream.py
noblklog/syslog.py
noblklog/util.py
noblklog.egg-info/PKG-INFO
noblklog.egg-info/SOURCES.txt
noblklog.egg-info/dependency_links.txt
noblklog.egg-info/top_level.txt