Metadata-Version: 2.1
Name: noblklog
Version: 0.1
Summary: Non-blocking asyncio handlers for Python logging.
Home-page: https://github.com/wagnerflo/noblklog
Author: Florian Wagner
Author-email: florian@wagner-flo.net
License: UNKNOWN
Platform: UNKNOWN
Classifier: Development Status :: 4 - Beta
Classifier: Framework :: AsyncIO
Classifier: Intended Audience :: Developers
Classifier: License :: OSI Approved :: Apache Software License
Classifier: Programming Language :: Python :: 3 :: Only
Classifier: Topic :: System :: Logging
Classifier: Topic :: Software Development :: Libraries :: Python Modules
Requires-Python: >=3.8
